kafka_lag_monitor/__init__.py
kafka_lag_monitor/main.py
kafka_lag_monitor/progress_bar.py
kafka_lag_monitor/schemas.py
kafka_lag_monitor/tui.py
kafka_lag_monitor/utils.py
kafka_lag_monitor-0.1.4.dist-info/LICENSE
kafka_lag_monitor-0.1.4.dist-info/METADATA
kafka_lag_monitor-0.1.4.dist-info/WHEEL
kafka_lag_monitor-0.1.4.dist-info/entry_points.txt
kafka_lag_monitor-0.1.4.dist-info/RECORD
