Metadata-Version: 2.1
Name: kafka-lag-monitor
Version: 0.1.4
Summary: 
Author: Ninad-Bhangui
Requires-Python: >=3.11,<4.0
Classifier: Programming Language :: Python :: 3
Classifier: Programming Language :: Python :: 3.11
Requires-Dist: pandas (>=2.1.4,<3.0.0)
Requires-Dist: paramiko (>=3.4.0,<4.0.0)
Requires-Dist: rich (>=13.7.0,<14.0.0)
Requires-Dist: tabulate (>=0.9.0,<0.10.0)
Requires-Dist: textual (>=0.47.1,<0.48.0)
Requires-Dist: typer[all] (>=0.9.0,<0.10.0)
